brom.py
pybrom-1.1.11.dist-info/METADATA
pybrom-1.1.11.dist-info/WHEEL
pybrom-1.1.11.dist-info/RECORD
