Metadata-Version: 2.1
Name: pybrom
Version: 1.1.11
Summary: Brom client
Home-page: https://brom.itworks.group
Author: Anton Rastyazhenko
Author-email: rastyazhenko.anton@gmail.com
Requires-Python: >=3.11,<4.0
Classifier: Programming Language :: Python :: 3
Classifier: Programming Language :: Python :: 3.11
Classifier: Programming Language :: Python :: 3.12
Requires-Dist: pydantic[email] (>=2.3.0,<3.0.0)
Requires-Dist: zeep[async] (>=4.2.1,<5.0.0)
Project-URL: Documentation, https://brom.itworks.group/documentation/python/
Project-URL: Repository, https://git.albus.keenetic.pro/Python/brom
